{"month":"2026-04","label":"2026년 4월","events":[{"title":"[경기] 수내 카드빈 - DIGIMON","start":"2026-04-17","allDay":true,"resultTitle":"디지몬 데일리 이벤트 결과","xUrl":"https://x.com/i/status/2045122697928257937"},{"title":"[경기] 수원 TCG TracerZ - ONE PIECE","start":"2026-04-17","allDay":true,"resultTitle":"원피스 스탠다드배틀 결과","xUrl":"https://x.com/i/status/2045111705441828995"},{"title":"[경기] 수원 TCG TracerZ - YUGIOH","start":"2026-04-17","allDay":true,"resultTitle":"유희왕 금요 토너먼트 결과","xUrl":"https://x.com/i/status/2045075258433241502"},{"title":"[경기] 일산 듀얼팩토리 - YUGIOH","start":"2026-04-17","allDay":true,"resultTitle":"유희왕의 날 대회 결과","xUrl":"https://x.com/i/status/2045127861305266293"},{"title":"[경기] 일산 듀얼팩토리 - VANGUARD","start":"2026-04-17","allDay":true,"resultTitle":"뱅가드 D 시즌 풀 대회 결과","xUrl":"https://x.com/i/status/2045127225406861551"},{"title":"[경남] 마산 Card Elixir - YUGIOH","start":"2026-04-17","allDay":true,"resultTitle":"유희왕 공인 토너먼트 결과","xUrl":"https://x.com/i/status/2045131450245374094"},{"title":"[서울] 장한평 마린포드 - YUGIOH","start":"2026-04-17","allDay":true,"resultTitle":"유희왕 1103 하프 CS 대회 결과","xUrl":"https://x.com/i/status/2045122410538848466"},{"title":"[서울] 장한평 마린포드 - NIVEL ARENA","start":"2026-04-17","allDay":true,"resultTitle":"니벨아레나 미니대회 결과","xUrl":"https://x.com/i/status/2045121897084645420"},{"title":"[서울] 장한평 마린포드 - DIGIMON","start":"2026-04-17","allDay":true,"resultTitle":"디지몬 LM 발매기념 미니대회 결과","xUrl":"https://x.com/i/status/2045121372373025007"},{"title":"[서울] 장한평 마린포드 - YUGIOH","start":"2026-04-17","allDay":true,"resultTitle":"유희왕 일본판 미니대회 결과","xUrl":"https://x.com/i/status/2045120755093139775"},{"title":"[인천] 부평 히어로즈 - YUGIOH","start":"2026-04-17","allDay":true,"resultTitle":"유희왕 비공인대회 결과","xUrl":"https://x.com/i/status/2045073622117879920"},{"title":"[경기] 수내 카드빈 - POKEMON","start":"2026-04-16","allDay":true,"resultTitle":"포켓몬 미니리그 공인 대회 결과","xUrl":"https://x.com/i/status/2044740373923455361"},{"title":"[서울] 당산 카드냥 - HOLOLIVE","start":"2026-04-16","allDay":true,"resultTitle":"홀로라이브 OCG 공인 샵대회 결과","xUrl":"https://x.com/i/status/2044747457167499449"},{"title":"[경기] 안산 LAS TCG - POKEMON","start":"2026-04-16","allDay":true,"resultTitle":"포켓몬 미니리그 결과","xUrl":"https://x.com/i/status/2045125094822023342"},{"title":"[경기] 안산 LAS TCG - YUGIOH","start":"2026-04-16","allDay":true,"resultTitle":"유희왕 미니리그 결과","xUrl":"https://x.com/i/status/2045123789181292719"},{"title":"[경기] 안산 LAS TCG - ONE PIECE","start":"2026-04-16","allDay":true,"resultTitle":"원피스 스탠다드 결과","xUrl":"https://x.com/i/status/2045123019946025084"},{"title":"[부산] 양정 J클로버 - HOLOLIVE","start":"2026-04-16","allDay":true,"resultTitle":"홀로라이브 평일 토너먼트 결과","xUrl":"https://x.com/i/status/2045017429664030985"},{"title":"[서울] 장한평 마린포드 - NIVEL ARENA","start":"2026-04-16","allDay":true,"resultTitle":"니벨아레나 미니대회 결과","xUrl":"https://x.com/i/status/2045121816335917519"},{"title":"[대구경북] 대구 듀얼스파크 - DIGIMON","start":"2026-04-15","allDay":true,"resultTitle":"디지몬 위클리 대회 결과","xUrl":"https://x.com/i/status/2044385524656542050"},{"title":"[대구경북] 대구 듀얼챔프 - ONE PIECE","start":"2026-04-15","allDay":true,"resultTitle":"원피스 스탠다드 대회 결과","xUrl":"https://x.com/i/status/2044352802554839513"},{"title":"[대구경북] 대구 듀얼챔프 - WEISS SCHWARZ","start":"2026-04-15","allDay":true,"resultTitle":"바이스 슈발츠 대회 결과","xUrl":"https://x.com/i/status/2044352802554839513"},{"title":"[대구경북] 대구 듀얼챔프 - HOLOLIVE","start":"2026-04-15","allDay":true,"resultTitle":"홀로라이브 캐쥬얼 대회 결과","xUrl":"https://x.com/i/status/2044352802554839513"},{"title":"[대구경북] 대구 듀얼챔프 - HOLOLIVE","start":"2026-04-15","allDay":true,"resultTitle":"홀로라이브 먼슬리 대회 결과","xUrl":"https://x.com/i/status/2044352802554839513"},{"title":"[대구경북] 대구 듀얼챔프 - WEISS SCHWARZ","start":"2026-04-15","allDay":true,"resultTitle":"바이스 슈발츠 매트대회 결과","xUrl":"https://x.com/i/status/2044344884468068651"},{"title":"[서울] 당산 카드냥 - DIGIMON","start":"2026-04-15","allDay":true,"resultTitle":"디지몬 테이머배틀 결과","xUrl":"https://x.com/i/status/2044384864053698942"},{"title":"[서울] 신당 카드스퀘어 - DIGIMON","start":"2026-04-15","allDay":true,"resultTitle":"디지몬 수달테 대회 결과","xUrl":"https://x.com/i/status/2044396932437881010"},{"title":"[서울] 잠실새내 카드스타 - DIGIMON","start":"2026-04-15","allDay":true,"resultTitle":"디지몬 최강 테이머 대회 결과","xUrl":"https://x.com/i/status/2044448135049838892"},{"title":"[서울] 장한평 마린포드 - YUGIOH","start":"2026-04-15","allDay":true,"resultTitle":"유희왕 일본판 미니대회 결과","xUrl":"https://x.com/i/status/2044398242939744385"},{"title":"[서울] 장한평 마린포드 - VANGUARD","start":"2026-04-15","allDay":true,"resultTitle":"뱅가드 일본판 미니대회 결과","xUrl":"https://x.com/i/status/2044397805201223939"},{"title":"[부산] 경성대 TCG 드로우 - YUGIOH","start":"2026-04-15","allDay":true,"resultTitle":"유희왕 한판풀 드로우 CS 결과","xUrl":"https://x.com/i/status/2044725064197910839"},{"title":"[부산] 양정 J클로버 - VANGUARD","start":"2026-04-15","allDay":true,"resultTitle":"뱅가드 평일 토너먼트 결과","xUrl":"https://x.com/i/status/2045017429664030985"},{"title":"[경기] 수내 카드빈 - ONE PIECE","start":"2026-04-14","allDay":true,"resultTitle":"원피스 스탠다드 배틀 결과","xUrl":"https://x.com/i/status/2044027130984718350"},{"title":"[대구경북] 대구 듀얼스파크 - VANGUARD","start":"2026-04-14","allDay":true,"resultTitle":"뱅가드 평일 대회 결과","xUrl":"https://x.com/i/status/2044026282049187944"},{"title":"[서울] 신당 카드스퀘어 - DIGIMON","start":"2026-04-14","allDay":true,"resultTitle":"디지몬 테이머 배틀 결과","xUrl":"https://x.com/i/status/2044029599638839793"},{"title":"[서울] 신당 카드스퀘어 - ONE PIECE","start":"2026-04-14","allDay":true,"resultTitle":"원피스 라프텔 CS 결과","xUrl":"https://x.com/i/status/2044023664551817702"},{"title":"[서울] 장한평 마린포드 - ONE PIECE","start":"2026-04-14","allDay":true,"resultTitle":"원피스 한글판 미니대회 결과","xUrl":"https://x.com/i/status/2044023826808483967"},{"title":"[서울] 장한평 마린포드 - YUGIOH RUSH DUEL","start":"2026-04-14","allDay":true,"resultTitle":"러시듀얼 CS 대회 결과","xUrl":"https://x.com/i/status/2044023342924214371"},{"title":"[서울] 장한평 마린포드 - VANGUARD","start":"2026-04-14","allDay":true,"resultTitle":"뱅가드 일본판 공인샵 토너먼트 결과","xUrl":"https://x.com/i/status/2044022364057591993"},{"title":"[서울] 장한평 마린포드 - YUGIOH","start":"2026-04-14","allDay":true,"resultTitle":"유희왕 일본판 미니대회 결과","xUrl":"https://x.com/i/status/2044021880164938158"},{"title":"[서울] 장한평 마린포드 - NIVEL ARENA","start":"2026-04-14","allDay":true,"resultTitle":"니벨아레나 미니대회 결과","xUrl":"https://x.com/i/status/2044020652152070194"},{"title":"[부산] 양정 J클로버 - YUGIOH","start":"2026-04-14","allDay":true,"resultTitle":"유희왕 평일 토너먼트 결과","xUrl":"https://x.com/i/status/2044280106886307897"},{"title":"[경기] 김포 카드베이스 - DIGIMON","start":"2026-04-13","allDay":true,"resultTitle":"디지몬 비공인 주말 위클리 결과","xUrl":"https://x.com/i/status/2043540053792895209"},{"title":"[경기] 김포 카드베이스 - HOLOLIVE","start":"2026-04-13","allDay":true,"resultTitle":"홀로라이브 OCG 먼슬리 샵 토너먼트 결과","xUrl":"https://x.com/i/status/2043539597083427202"},{"title":"[서울] 송파 카드피아 - WEISS SCHWARZ","start":"2026-04-13","allDay":true,"resultTitle":"바이스 슈발츠 18주년 기념 대회 결과","xUrl":"https://x.com/i/status/2043606130979729647"},{"title":"[서울] 송파 카드피아 - LUMEN CONDENSOR","start":"2026-04-13","allDay":true,"resultTitle":"루멘콘덴서 제 2 회 공기공기밥 컵 결과","xUrl":"https://x.com/i/status/2043592238710899119"},{"title":"[경기] 수내 카드빈 - ONE PIECE","start":"2026-04-12","allDay":true,"resultTitle":"원피스 플래그쉽 배틀 결과","xUrl":"https://x.com/i/status/2043219518831702384"},{"title":"[경기] 수원 TCG TracerZ - YUGIOH","start":"2026-04-12","allDay":true,"resultTitle":"유희왕 SUN DAY 토너먼트 결과","xUrl":"https://x.com/i/status/2043279333704532459"},{"title":"[경기] 수원 TCG TracerZ - DIGIMON","start":"2026-04-12","allDay":true,"resultTitle":"디지몬 일판 테이머배틀 결과","xUrl":"https://x.com/i/status/2043276812776853540"},{"title":"[경기] 수원 TCG TracerZ - DIGIMON","start":"2026-04-12","allDay":true,"resultTitle":"디지몬 한판 테이머배틀 결과","xUrl":"https://x.com/i/status/2043245198214586697"},{"title":"[경기] 수원 TCG TracerZ - DIGIMON","start":"2026-04-12","allDay":true,"resultTitle":"디지몬 레귤레이션 배틀 결과","xUrl":"https://x.com/i/status/2043233833093664804"},{"title":"[경기] 안산 LAS TCG - WEISS SCHWARZ","start":"2026-04-12","allDay":true,"resultTitle":"바이스슈발츠 공인대회 결과","xUrl":"https://x.com/i/status/2043300149825585547"},{"title":"[경기] 안산 LAS TCG - NIVEL ARENA","start":"2026-04-12","allDay":true,"resultTitle":"니벨아레나 미니리그 결과","xUrl":"https://x.com/i/status/2043298627033186370"},{"title":"[경기] 일산 듀얼팩토리 - NIVEL ARENA","start":"2026-04-12","allDay":true,"resultTitle":"니벨아레나 레벨업 리그 대회 결과","xUrl":"https://x.com/i/status/2043249627374535124"},{"title":"[경기] 일산 듀얼팩토리 - UNION ARENA","start":"2026-04-12","allDay":true,"resultTitle":"유니온 아레나 비공인 대회 결과","xUrl":"https://x.com/i/status/2043247991860191538"},{"title":"[경기] 일산 듀얼팩토리 - VANGUARD","start":"2026-04-12","allDay":true,"resultTitle":"뱅가드 D 시즌 공인 대회 결과","xUrl":"https://x.com/i/status/2043228441026461784"},{"title":"[경남] 울산 던전다이스 - HOLOLIVE","start":"2026-04-12","allDay":true,"resultTitle":"홀로라이브 먼슬리 대회 결과","xUrl":"https://x.com/i/status/2043188458773209586"},{"title":"[대구경북] 대구 듀얼스파크 - ONE PIECE","start":"2026-04-12","allDay":true,"resultTitle":"원피스 하치노스 CS 결과","xUrl":"https://x.com/i/status/2043361884863389968"},{"title":"[대구경북] 대구 듀얼스파크 - WEISS SCHWARZ","start":"2026-04-12","allDay":true,"resultTitle":"바이스슈발츠 공인대회 결과","xUrl":"https://x.com/i/status/2043249316178080146"},{"title":"[부산] 동래 티씨지샵 셔플 - VANGUARD","start":"2026-04-12","allDay":true,"resultTitle":"뱅가드 샵파이트 결과","xUrl":"https://x.com/i/status/2043225911110324318"},{"title":"[부산] 동래 티씨지샵 셔플 - POKEMON","start":"2026-04-12","allDay":true,"resultTitle":"포켓몬 카드게임 미니리그 결과","xUrl":"https://x.com/i/status/2043223471573065777"},{"title":"[부산] 동래 티씨지샵 셔플 - NIVEL ARENA","start":"2026-04-12","allDay":true,"resultTitle":"니벨아레나 레벨업리그 결과","xUrl":"https://x.com/i/status/2043223189925577197"},{"title":"[서울] 당산 카드냥 - DIGIMON","start":"2026-04-12","allDay":true,"resultTitle":"디지몬 테이머배틀 결과","xUrl":"https://x.com/i/status/2043302611089342493"},{"title":"[서울] 신사 포카드 - ONE PIECE","start":"2026-04-12","allDay":true,"resultTitle":"원피스 위클리 대회 결과","xUrl":"https://x.com/i/status/2043224548569645270"},{"title":"[서울] 잠실새내 카드스타 - Stacker Battle","start":"2026-04-12","allDay":true,"resultTitle":"스태커배틀 미니대회 결과","xUrl":"https://x.com/i/status/2043243121279131649"},{"title":"[서울] 장한평 마린포드 - NIVEL ARENA","start":"2026-04-12","allDay":true,"resultTitle":"니벨아레나 CS 결과","xUrl":"https://x.com/i/status/2043324501505814836"},{"title":"[서울] 장한평 마린포드 - YUGIOH","start":"2026-04-12","allDay":true,"resultTitle":"유희왕 게이트볼 결과","xUrl":"https://x.com/i/status/2043323891926618309"},{"title":"[서울] 장한평 마린포드 - YUGIOH","start":"2026-04-12","allDay":true,"resultTitle":"유희왕 일본판 미니대회 결과","xUrl":"https://x.com/i/status/2043323329093029942"},{"title":"[인천] 부평 히어로즈 - DIGIMON","start":"2026-04-12","allDay":true,"resultTitle":"디지몬 테이머 배틀 대회 결과","xUrl":"https://x.com/i/status/2043268270627946825"},{"title":"[인천] 부평 히어로즈 - DIGIMON","start":"2026-04-12","allDay":true,"resultTitle":"디지몬 에볼루션컵 대회 결과","xUrl":"https://x.com/i/status/2043248620099760465"},{"title":"[부산] 양정 J클로버 - YUGIOH","start":"2026-04-12","allDay":true,"resultTitle":"유희왕 주말 입상 결과","xUrl":"https://x.com/i/status/2043571231598018750"},{"title":"[부산] 양정 J클로버 - WEISS SCHWARZ","start":"2026-04-12","allDay":true,"resultTitle":"바이스 슈발츠 주말 입상 결과","xUrl":"https://x.com/i/status/2043571231598018750"},{"title":"[부산] 양정 J클로버 - HOLOLIVE","start":"2026-04-12","allDay":true,"resultTitle":"홀로라이브 주말 입상 결과","xUrl":"https://x.com/i/status/2043571231598018750"},{"title":"[인천] 부평 히어로즈 - YUGIOH","start":"2026-04-12","allDay":true,"resultTitle":"유희왕 비공인대회 결과","xUrl":"https://x.com/i/status/2043523826043273307"},{"title":"[경기] 평택 카드빌리지 - YUGIOH","start":"2026-04-12","allDay":true,"resultTitle":"유희왕 미니대회 결과","xUrl":"https://x.com/i/status/2044645921309479419"},{"title":"[경기] 평택 카드빌리지 - DIGIMON","start":"2026-04-12","allDay":true,"resultTitle":"디지몬 미니 대회 결과","xUrl":"https://x.com/i/status/2044645876539482409"},{"title":"[경기] 평택 카드빌리지 - NIVEL ARENA","start":"2026-04-12","allDay":true,"resultTitle":"니벨 레벨업 리그 대회 결과","xUrl":"https://x.com/i/status/2044645824274268516"},{"title":"[경기] 평택 카드빌리지 - DIGIMON","start":"2026-04-12","allDay":true,"resultTitle":"디지몬 레귤레이션 배틀 대회 결과","xUrl":"https://x.com/i/status/2044645726622490798"},{"title":"[경기] 수내 카드빈 - DIGIMON","start":"2026-04-11","allDay":true,"resultTitle":"디지몬 위클리 이벤트 결과","xUrl":"https://x.com/i/status/2042932225348604251"},{"title":"[경기] 수내 카드빈 - DIGIMON","start":"2026-04-11","allDay":true,"resultTitle":"디지몬 3:3 팀전 이벤트 결과","xUrl":"https://x.com/i/status/2042873355741942191"},{"title":"[경기] 수원 TCG TracerZ - YUGIOH","start":"2026-04-11","allDay":true,"resultTitle":"유희왕 제 74 회 TTZ-CS 토너먼트 결과","xUrl":"https://x.com/i/status/2042923687423414730"},{"title":"[경기] 안산 LAS TCG - DIGIMON","start":"2026-04-11","allDay":true,"resultTitle":"디지몬 미니리그 결과","xUrl":"https://x.com/i/status/2042958653054161299"},{"title":"[경기] 안산 LAS TCG - HOLOLIVE","start":"2026-04-11","allDay":true,"resultTitle":"홀로라이브 공인대회 결과","xUrl":"https://x.com/i/status/2042958420656246927"},{"title":"[경기] 일산 듀얼팩토리 - DIGIMON","start":"2026-04-11","allDay":true,"resultTitle":"디지몬 테이머 배틀 대회 결과","xUrl":"https://x.com/i/status/2042906216998015424"},{"title":"[경기] 일산 듀얼팩토리 - HOLOLIVE","start":"2026-04-11","allDay":true,"resultTitle":"홀로라이브 OCG 공인 대회 결과","xUrl":"https://x.com/i/status/2042903589811818564"},{"title":"[경기] 일산 듀얼팩토리 - ONE PIECE","start":"2026-04-11","allDay":true,"resultTitle":"원피스 스탠다드 배틀 결과","xUrl":"https://x.com/i/status/2042879092958335203"},{"title":"[경기] 일산 듀얼팩토리 - VANGUARD","start":"2026-04-11","allDay":true,"resultTitle":"뱅가드 D 시즌 샵파이트 대회 결과","xUrl":"https://x.com/i/status/2042876105510768829"},{"title":"[경기] 일산 듀얼팩토리 - Stacker Battle","start":"2026-04-11","allDay":true,"resultTitle":"스태커배틀 스타터 대회 결과","xUrl":"https://x.com/i/status/2042870251998810476"},{"title":"[경남] 성산 TCG라이프 - DIGIMON","start":"2026-04-11","allDay":true,"resultTitle":"디지몬 비공인 대회 결과","xUrl":"https://x.com/i/status/2042921537939083765"},{"title":"[경남] 성산 TCG라이프 - YUGIOH","start":"2026-04-11","allDay":true,"resultTitle":"유희왕 비공인 대회 결과","xUrl":"https://x.com/i/status/2042921096694108483"},{"title":"[경남] 울산 던전다이스 - DIGIMON","start":"2026-04-11","allDay":true,"resultTitle":"디지몬 레귤레이션 대회 결과","xUrl":"https://x.com/i/status/2042854322934026280"},{"title":"[경남] 울산 던전다이스 - WEISS SCHWARZ","start":"2026-04-11","allDay":true,"resultTitle":"바이스 슈발츠 18 주년 대회 결과","xUrl":"https://x.com/i/status/2042852184593961109"},{"title":"[대구경북] 대구 듀얼스파크 - DIGIMON","start":"2026-04-11","allDay":true,"resultTitle":"디지몬 테이머 배틀 결과","xUrl":"https://x.com/i/status/2042911649171144890"},{"title":"[대구경북] 대구 듀얼스파크 - YUGIOH","start":"2026-04-11","allDay":true,"resultTitle":"유희왕 WCQ 공인 토너먼트 결과","xUrl":"https://x.com/i/status/2042910830250070187"},{"title":"[대구경북] 대구 듀얼챔프 - YUGIOH","start":"2026-04-11","allDay":true,"resultTitle":"유희왕 듀얼챔프 대회 결과","xUrl":"https://x.com/i/status/2042954737826541948"},{"title":"[서울] 당산 카드냥 - LUMEN CONDENSOR","start":"2026-04-11","allDay":true,"resultTitle":"루멘콘덴서 공인대회 결과","xUrl":"https://x.com/i/status/2042868604694335581"},{"title":"[서울] 당산 카드냥 - YUGIOH RUSH DUEL","start":"2026-04-11","allDay":true,"resultTitle":"러시듀얼 먼슬리 토너먼트 결과","xUrl":"https://x.com/i/status/2042868285860122925"},{"title":"[서울] 신당 카드스퀘어 - DIGIMON","start":"2026-04-11","allDay":true,"resultTitle":"디지몬 테이머 배틀 결과","xUrl":"https://x.com/i/status/2042867926827516019"},{"title":"[서울] 신당 카드스퀘어 - DIGIMON","start":"2026-04-11","allDay":true,"resultTitle":"디지몬 에볼루션컵 결과","xUrl":"https://x.com/i/status/2042867506621354295"},{"title":"[서울] 잠실새내 카드스타 - LUMEN CONDENSOR","start":"2026-04-11","allDay":true,"resultTitle":"루멘콘덴서 미니대회 결과","xUrl":"https://x.com/i/status/2042931420130336846"},{"title":"[서울] 장한평 마린포드 - YUGIOH","start":"2026-04-11","allDay":true,"resultTitle":"유희왕 일본판 미니대회 결과","xUrl":"https://x.com/i/status/2042952196938228123"},{"title":"[서울] 장한평 마린포드 - DIGIMON","start":"2026-04-11","allDay":true,"resultTitle":"디지몬 카드게임 대회 결과","xUrl":"https://x.com/i/status/2042949125608739022"},{"title":"[서울] 장한평 마린포드 - NIVEL ARENA","start":"2026-04-11","allDay":true,"resultTitle":"니벨아레나 레벨업 리그 결과","xUrl":"https://x.com/i/status/2042948258876854459"},{"title":"[인천] 부평 히어로즈 - YUGIOH","start":"2026-04-11","allDay":true,"resultTitle":"유희왕 비공인대회 결과","xUrl":"https://x.com/i/status/2042947284619632665"},{"title":"[전라제주] 제주 TCG아일랜드 - VANGUARD","start":"2026-04-11","allDay":true,"resultTitle":"뱅가드 발매기념 대회 결과","xUrl":"https://x.com/i/status/2042904429792497870"},{"title":"[전라제주] 제주 TCG아일랜드 - VANGUARD","start":"2026-04-11","allDay":true,"resultTitle":"뱅가드 정기 대회 결과","xUrl":"https://x.com/i/status/2042900401872392404"},{"title":"[인천] 주안 티씨지아레나 - DIGIMON","start":"2026-04-11","allDay":true,"resultTitle":"디지몬 에볼루션컵 결과","xUrl":"https://x.com/i/status/2043171944162590861"},{"title":"[전라제주] 제주 TCG아일랜드 - YUGIOH","start":"2026-04-11","allDay":true,"resultTitle":"유희왕 정기 대회 결과","xUrl":"https://x.com/i/status/2043257832477520215"},{"title":"[부산] 양정 J클로버 - DIGIMON","start":"2026-04-11","allDay":true,"resultTitle":"디지몬 주말 입상 결과","xUrl":"https://x.com/i/status/2043570861693911437"},{"title":"[부산] 양정 J클로버 - VANGUARD","start":"2026-04-11","allDay":true,"resultTitle":"카드파이트 뱅가드 주말 입상 결과","xUrl":"https://x.com/i/status/2043570861693911437"},{"title":"[부산] 양정 J클로버 - WEISS SCHWARZ","start":"2026-04-11","allDay":true,"resultTitle":"바이스 슈발츠 주말 입상 결과","xUrl":"https://x.com/i/status/2043570861693911437"},{"title":"[충남충북] 천안 카드빌리지 - HOLOLIVE","start":"2026-04-11","allDay":true,"resultTitle":"홀로라이브 공인 샵 대회 결과","xUrl":"https://x.com/i/status/2044040307780841560"},{"title":"[경기] 평택 카드빌리지 - DIGIMON","start":"2026-04-11","allDay":true,"resultTitle":"디지몬 테이머배틀 대회 결과","xUrl":"https://x.com/i/status/2044645588525076629"},{"title":"[경기] 김포 카드베이스 - DIGIMON","start":"2026-04-10","allDay":true,"resultTitle":"디지몬 비공인 평일 위클리 결과","xUrl":"https://x.com/i/status/2042601499080167837"},{"title":"[경기] 수내 카드빈 - DIGIMON","start":"2026-04-10","allDay":true,"resultTitle":"디지몬 위클리 이벤트 결과","xUrl":"https://x.com/i/status/2042582901158744253"},{"title":"[경기] 안산 LAS TCG - POKEMON","start":"2026-04-10","allDay":true,"resultTitle":"포켓몬 미니리그 결과","xUrl":"https://x.com/i/status/2042582509872123989"},{"title":"[경기] 일산 듀얼팩토리 - NIVEL ARENA","start":"2026-04-10","allDay":true,"resultTitle":"니벨아레나 비공인 대회 결과","xUrl":"https://x.com/i/status/2042567900113047745"},{"title":"[대구경북] 대구 듀얼스파크 - ONE PIECE","start":"2026-04-10","allDay":true,"resultTitle":"원피스 스탠다드 배틀 결과","xUrl":"https://x.com/i/status/2042564749603541397"},{"title":"[부산] 양정 J클로버 - YUGIOH","start":"2026-04-10","allDay":true,"resultTitle":"유희왕 토너먼트 결과","xUrl":"https://x.com/i/status/2042597226913108015"},{"title":"[부산] 양정 J클로버 - ONE PIECE","start":"2026-04-10","allDay":true,"resultTitle":"원피스 카드게임 토너먼트 결과","xUrl":"https://x.com/i/status/2042597226913108015"},{"title":"[서울] 당산 카드냥 - VANGUARD","start":"2026-04-10","allDay":true,"resultTitle":"뱅가드 샵파이트 결과","xUrl":"https://x.com/i/status/2042569096211091699"},{"title":"[서울] 당산 카드냥 - ONE PIECE","start":"2026-04-10","allDay":true,"resultTitle":"원피스 스탠다드 배틀 결과","xUrl":"https://x.com/i/status/2042568914723573998"},{"title":"[서울] 신당 카드스퀘어 - DIGIMON","start":"2026-04-10","allDay":true,"resultTitle":"디지몬 미니대회 결과","xUrl":"https://x.com/i/status/2042593791887183986"},{"title":"[서울] 신당 카드스퀘어 - YUGIOH","start":"2026-04-10","allDay":true,"resultTitle":"유희왕 백수팬더 CS 결과","xUrl":"https://x.com/i/status/2042593486986449086"},{"title":"[서울] 장한평 마린포드 - YUGIOH","start":"2026-04-10","allDay":true,"resultTitle":"유희왕 게이트볼 대회 입상 결과","xUrl":"https://x.com/i/status/2042589339646071064"},{"title":"[서울] 장한평 마린포드 - VANGUARD","start":"2026-04-10","allDay":true,"resultTitle":"뱅가드 한글판 CS 결과","xUrl":"https://x.com/i/status/2042587452691615874"},{"title":"[서울] 장한평 마린포드 - DIGIMON","start":"2026-04-10","allDay":true,"resultTitle":"디지몬 미니대회 입상 결과","xUrl":"https://x.com/i/status/2042587226127642747"},{"title":"[경기] 수내 카드빈 - POKEMON","start":"2026-04-09","allDay":true,"resultTitle":"포켓몬 미니리그 공인 대회 결과","xUrl":"https://x.com/i/status/2042208917850349587"},{"title":"[대구경북] 대구 듀얼스파크 - DIGIMON","start":"2026-04-09","allDay":true,"resultTitle":"디지몬 위클리 배틀 결과","xUrl":"https://x.com/i/status/2042196994777928085"},{"title":"[서울] 당산 카드냥 - HOLOLIVE","start":"2026-04-09","allDay":true,"resultTitle":"홀로라이브 공인 샵대회 결과","xUrl":"https://x.com/i/status/2042205335608586449"},{"title":"[부산] 양정 J클로버 - HOLOLIVE","start":"2026-04-09","allDay":true,"resultTitle":"홀로라이브 토너먼트 결과","xUrl":"https://x.com/i/status/2042597226913108015"},{"title":"[서울] 장한평 마린포드 - YUGIOH","start":"2026-04-09","allDay":true,"resultTitle":"유희왕 일본판 미니대회 입상 결과","xUrl":"https://x.com/i/status/2042516932881191082"},{"title":"[서울] 장한평 마린포드 - DIGIMON","start":"2026-04-09","allDay":true,"resultTitle":"디지몬 카드게임 테이머 배틀 결과","xUrl":"https://x.com/i/status/2042885891056926959"},{"title":"[충남충북] 천안 카드빌리지 - DIGIMON","start":"2026-04-09","allDay":true,"resultTitle":"디지몬 정기 미니리그 결과","xUrl":"https://x.com/i/status/2044040238985887999"},{"title":"[서울] 당산 카드냥 - DIGIMON","start":"2026-04-08","allDay":true,"resultTitle":"디지몬 테이머배틀 결과","xUrl":"https://x.com/i/status/2041854955473268844"},{"title":"[서울] 신당 카드스퀘어 - DIGIMON","start":"2026-04-08","allDay":true,"resultTitle":"디지몬 수요일을 달리는 테이머 결과","xUrl":"https://x.com/i/status/2041857056668594327"},{"title":"[서울] 잠실새내 카드스타 - DIGIMON","start":"2026-04-08","allDay":true,"resultTitle":"디지몬 최강 테이머 6 회차 대회 결과","xUrl":"https://x.com/i/status/2041888619137528279"},{"title":"[서울] 장한평 마린포드 - VANGUARD","start":"2026-04-08","allDay":true,"resultTitle":"뱅가드 미니대회 결과","xUrl":"https://x.com/i/status/2041871849748099143"},{"title":"[서울] 장한평 마린포드 - YUGIOH","start":"2026-04-08","allDay":true,"resultTitle":"유희왕 일본판 미니대회 결과","xUrl":"https://x.com/i/status/2041871594302402688"},{"title":"[경기] 안산 LAS TCG - SHADOWVERSE EVOLVE","start":"2026-04-08","allDay":true,"resultTitle":"섀도우버스 이볼브 공인대회 결과","xUrl":"https://x.com/i/status/2042581928172572922"},{"title":"[부산] 양정 J클로버 - VANGUARD","start":"2026-04-08","allDay":true,"resultTitle":"카드파이트뱅가드 토너먼트 결과","xUrl":"https://x.com/i/status/2042597226913108015"},{"title":"[충남충북] 천안 카드빌리지 - ONE PIECE","start":"2026-04-08","allDay":true,"resultTitle":"원피스 리미티드 배틀 결과","xUrl":"https://x.com/i/status/2044040128566571201"},{"title":"[경기] 수내 카드빈 - ONE PIECE","start":"2026-04-07","allDay":true,"resultTitle":"원피스 스탠다드 배틀 결과","xUrl":"https://x.com/i/status/2041500129015046417"},{"title":"[대구경북] 대구 듀얼스파크 - VANGUARD","start":"2026-04-07","allDay":true,"resultTitle":"뱅가드 평일 대회 결과","xUrl":"https://x.com/i/status/2041479531027128585"},{"title":"[서울] 신당 카드스퀘어 - DIGIMON","start":"2026-04-07","allDay":true,"resultTitle":"디지몬 테이머 배틀 결과","xUrl":"https://x.com/i/status/2041487967160799519"},{"title":"[서울] 신당 카드스퀘어 - ONE PIECE","start":"2026-04-07","allDay":true,"resultTitle":"원피스 라프텔 CS 결과","xUrl":"https://x.com/i/status/2041487872117944665"},{"title":"[서울] 장한평 마린포드 - VANGUARD","start":"2026-04-07","allDay":true,"resultTitle":"뱅가드 공인샵 토너먼트 결과","xUrl":"https://x.com/i/status/2041506795609571601"},{"title":"[서울] 장한평 마린포드 - ONE PIECE","start":"2026-04-07","allDay":true,"resultTitle":"원피스 카드게임 대회 결과","xUrl":"https://x.com/i/status/2041506222721945903"},{"title":"[서울] 장한평 마린포드 - YUGIOH","start":"2026-04-07","allDay":true,"resultTitle":"유희왕 일본판 미니대회 결과","xUrl":"https://x.com/i/status/2041505915552280957"},{"title":"[서울] 장한평 마린포드 - YUGIOH RUSH DUEL","start":"2026-04-07","allDay":true,"resultTitle":"러시듀얼 대회 결과","xUrl":"https://x.com/i/status/2041505730239558093"},{"title":"[부산] 양정 J클로버 - YUGIOH","start":"2026-04-07","allDay":true,"resultTitle":"유희왕 토너먼트 결과","xUrl":"https://x.com/i/status/2042597226913108015"},{"title":"[서울] 장한평 마린포드 - NIVEL ARENA","start":"2026-04-06","allDay":true,"resultTitle":"니벨아레나 미니대회 결과","xUrl":"https://x.com/i/status/2041127415091765455"},{"title":"[서울] 장한평 마린포드 - YUGIOH","start":"2026-04-06","allDay":true,"resultTitle":"유희왕 일본판 미니대회 결과","xUrl":"https://x.com/i/status/2041125870895759846"},{"title":"[충남충북] 천안 카드빌리지 - YUGIOH","start":"2026-04-06","allDay":true,"resultTitle":"유희왕 정기 미니리그 결과","xUrl":"https://x.com/i/status/2044040073008820676"},{"title":"[경기] 김포 카드베이스 - DIGIMON","start":"2026-04-05","allDay":true,"resultTitle":"디지몬 비공인 3on3 토너먼트 결과","xUrl":"https://x.com/i/status/2040751500398678324"},{"title":"[경기] 수원 TCG TracerZ - DIGIMON","start":"2026-04-05","allDay":true,"resultTitle":"디지몬 테이머배틀 결과","xUrl":"https://x.com/i/status/2040744397562884507"},{"title":"[경기] 수원 TCG TracerZ - DIGIMON","start":"2026-04-05","allDay":true,"resultTitle":"디지몬 에볼루션컵 대회 결과","xUrl":"https://x.com/i/status/2040716712103088633"},{"title":"[경기] 안산 LAS TCG - WEISS SCHWARZ","start":"2026-04-05","allDay":true,"resultTitle":"바이스 슈발츠 공인대회 결과","xUrl":"https://x.com/i/status/2040753246328037885"},{"title":"[경기] 안산 LAS TCG - NIVEL ARENA","start":"2026-04-05","allDay":true,"resultTitle":"니벨아레나 미니리그 결과","xUrl":"https://x.com/i/status/2040736308340072687"},{"title":"[경기] 일산 듀얼팩토리 - DIGIMON","start":"2026-04-05","allDay":true,"resultTitle":"디지몬 에볼루션 컵 대회 결과","xUrl":"https://x.com/i/status/2040727227411951958"},{"title":"[경기] 일산 듀얼팩토리 - VANGUARD","start":"2026-04-05","allDay":true,"resultTitle":"뱅가드 공인 및 풀 대회 결과","xUrl":"https://x.com/i/status/2040725475388276972"},{"title":"[경남] 울산 던전다이스 - DIGIMON","start":"2026-04-05","allDay":true,"resultTitle":"디지몬 에볼 컵 및 테이머 배틀 대회 결과","xUrl":"https://x.com/i/status/2040739549085864277"},{"title":"[경남] 울산 던전다이스 - WEISS SCHWARZ","start":"2026-04-05","allDay":true,"resultTitle":"바이스 슈발츠 비공인 대회 결과","xUrl":"https://x.com/i/status/2040696653523652867"},{"title":"[경남] 울산 던전다이스 - HOLOLIVE","start":"2026-04-05","allDay":true,"resultTitle":"홀로라이브 대회 결과","xUrl":"https://x.com/i/status/2040684656593625409"},{"title":"[경남] 울산 듀얼팩토리 - YUGIOH","start":"2026-04-05","allDay":true,"resultTitle":"유희왕 비공인 토너먼트 결과","xUrl":"https://x.com/i/status/2040756384653087160"},{"title":"[경남] 울산 듀얼팩토리 - DIGIMON","start":"2026-04-05","allDay":true,"resultTitle":"디지몬 테이머 배틀 결과","xUrl":"https://x.com/i/status/2040755794023727342"},{"title":"[경남] 울산 듀얼팩토리 - POKEMON","start":"2026-04-05","allDay":true,"resultTitle":"포켓몬 공인 토너먼트 결과","xUrl":"https://x.com/i/status/2040755566612717740"},{"title":"[대구경북] 대구 듀얼스파크 - ONE PIECE","start":"2026-04-05","allDay":true,"resultTitle":"원피스 플래그쉽 배틀 결과","xUrl":"https://x.com/i/status/2040692768562172317"},{"title":"[부산] 경성대 TCG 드로우 - DIGIMON","start":"2026-04-05","allDay":true,"resultTitle":"디지몬 테이머 배틀 결과","xUrl":"https://x.com/i/status/2040775577775542304"},{"title":"[부산] 경성대 TCG 드로우 - DIGIMON","start":"2026-04-05","allDay":true,"resultTitle":"디지몬 에볼루션컵 2026 시즌 2 결과","xUrl":"https://x.com/i/status/2040771172099649854"},{"title":"[부산] 경성대 TCG 드로우 - ONE PIECE","start":"2026-04-05","allDay":true,"resultTitle":"원피스 스탠다드배틀 대회 결과","xUrl":"https://x.com/i/status/2040744695501082842"},{"title":"[부산] 동래 티씨지샵 셔플 - POKEMON","start":"2026-04-05","allDay":true,"resultTitle":"포켓몬 카드 게임 미니리그 결과","xUrl":"https://x.com/i/status/2040704202943709363"},{"title":"[부산] 동래 티씨지샵 셔플 - VANGUARD","start":"2026-04-05","allDay":true,"resultTitle":"뱅가드 샵파이트 결과","xUrl":"https://x.com/i/status/2040701095513866750"},{"title":"[부산] 동래 티씨지샵 셔플 - NIVEL ARENA","start":"2026-04-05","allDay":true,"resultTitle":"니벨아레나 비공인 샵대회 결과","xUrl":"https://x.com/i/status/2040678006885351769"},{"title":"[서울] 신사 포카드 - POKEMON","start":"2026-04-05","allDay":true,"resultTitle":"포켓몬 위클리 대회 결과","xUrl":"https://x.com/i/status/2040690225471782925"},{"title":"[서울] 신사 포카드 - ONE PIECE","start":"2026-04-05","allDay":true,"resultTitle":"원피스 위클리 대회 결과","xUrl":"https://x.com/i/status/2040690035843023264"},{"title":"[서울] 장한평 마린포드 - NIVEL ARENA","start":"2026-04-05","allDay":true,"resultTitle":"니벨아레나 CS 결과","xUrl":"https://x.com/i/status/2040766419206582483"},{"title":"[서울] 장한평 마린포드 - VANGUARD","start":"2026-04-05","allDay":true,"resultTitle":"뱅가드 대회 결과","xUrl":"https://x.com/i/status/2040764141556945046"},{"title":"[서울] 장한평 마린포드 - YUGIOH","start":"2026-04-05","allDay":true,"resultTitle":"유희왕 일본판 미니대회 결과","xUrl":"https://x.com/i/status/2040763530673340800"},{"title":"[서울] 장한평 마린포드 - YUGIOH","start":"2026-04-05","allDay":true,"resultTitle":"유희왕 무금제 대회 결과","xUrl":"https://x.com/i/status/2040761992101937608"},{"title":"[인천] 부평 히어로즈 - YUGIOH","start":"2026-04-05","allDay":true,"resultTitle":"유희왕 비공인대회 결과","xUrl":"https://x.com/i/status/2040733090335928542"},{"title":"[전라제주] 제주 TCG아일랜드 - YUGIOH","start":"2026-04-05","allDay":true,"resultTitle":"유희왕 정기대회 결과","xUrl":"https://x.com/i/status/2040710223498010743"},{"title":"[전라제주] 목포 TCG팩토리 - ONE PIECE","start":"2026-04-05","allDay":true,"resultTitle":"원피스 카드게임 크로스 CS 3on3 목포 대회 결과","xUrl":"https://x.com/i/status/2041009175405473833"},{"title":"[대구경북] 대구 듀얼스파크 - ONE PIECE","start":"2026-04-05","allDay":true,"resultTitle":"원피스 하치노스 CS 결과","xUrl":"https://x.com/i/status/2041474557136302348"},{"title":"[부산] 양정 J클로버 - YUGIOH","start":"2026-04-05","allDay":true,"resultTitle":"유희왕 공인 토너먼트 결과","xUrl":"https://x.com/i/status/2041409472904749073"},{"title":"[부산] 양정 J클로버 - WEISS SCHWARZ","start":"2026-04-05","allDay":true,"resultTitle":"바이스 슈발츠 토너먼트 결과","xUrl":"https://x.com/i/status/2041409472904749073"},{"title":"[부산] 양정 J클로버 - HOLOLIVE","start":"2026-04-05","allDay":true,"resultTitle":"홀로라이브 토너먼트 결과","xUrl":"https://x.com/i/status/2041409472904749073"},{"title":"[경기] 평택 카드빌리지 - YUGIOH","start":"2026-04-05","allDay":true,"resultTitle":"유희왕 미니대회 결과","xUrl":"https://x.com/i/status/2042502830582530412"},{"title":"[경기] 평택 카드빌리지 - DIGIMON","start":"2026-04-05","allDay":true,"resultTitle":"디지몬 미니대회 결과","xUrl":"https://x.com/i/status/2042502297302024312"},{"title":"[충남충북] 천안 카드빌리지 - POKEMON","start":"2026-04-05","allDay":true,"resultTitle":"포켓몬 카드게임 공인 미니리그 결과","xUrl":"https://x.com/i/status/2042421537647837459"},{"title":"[경기] 김포 카드베이스 - HOLOLIVE","start":"2026-04-04","allDay":true,"resultTitle":"홀로라이브 OCG 익스트리머 컵 결과","xUrl":"https://x.com/i/status/2040336650715517434"},{"title":"[경기] 수내 카드빈 - DIGIMON","start":"2026-04-04","allDay":true,"resultTitle":"디지몬 위클리 이벤트 결과","xUrl":"https://x.com/i/status/2040393159172317287"},{"title":"[경기] 안산 LAS TCG - DIGIMON","start":"2026-04-04","allDay":true,"resultTitle":"디지몬 미니리그 결과","xUrl":"https://x.com/i/status/2040407573044850858"},{"title":"[경기] 안산 LAS TCG - HOLOLIVE","start":"2026-04-04","allDay":true,"resultTitle":"홀로라이브 공인대회 결과","xUrl":"https://x.com/i/status/2040407241799675949"},{"title":"[경기] 안산 LAS TCG - WEISS SCHWARZ","start":"2026-04-04","allDay":true,"resultTitle":"바이스슈발츠 18 주년 대회 결과","xUrl":"https://x.com/i/status/2040404984731480092"},{"title":"[경기] 일산 듀얼팩토리 - DIGIMON","start":"2026-04-04","allDay":true,"resultTitle":"디지몬 카드게임 테이머 배틀 대회 결과","xUrl":"https://x.com/i/status/2040392913549709336"},{"title":"[경기] 일산 듀얼팩토리 - UNION ARENA","start":"2026-04-04","allDay":true,"resultTitle":"유니온 아레나 2 인 팀전 대회 결과","xUrl":"https://x.com/i/status/2040355860887781747"},{"title":"[경기] 일산 듀얼팩토리 - NIVEL ARENA","start":"2026-04-04","allDay":true,"resultTitle":"니벨아레나 비공인 대회 결과","xUrl":"https://x.com/i/status/2040350858177904692"},{"title":"[경기] 일산 듀얼팩토리 - HOLOLIVE","start":"2026-04-04","allDay":true,"resultTitle":"홀로라이브 OCG 공인 대회 결과","xUrl":"https://x.com/i/status/2040321925462077819"},{"title":"[대구경북] 대구 듀얼스파크 - DIGIMON","start":"2026-04-04","allDay":true,"resultTitle":"디지몬 테이머 배틀 결과","xUrl":"https://x.com/i/status/2040432274815299958"},{"title":"[대구경북] 대구 듀얼스파크 - VANGUARD","start":"2026-04-04","allDay":true,"resultTitle":"뱅가드 주말 대회 결과","xUrl":"https://x.com/i/status/2040266019906912337"},{"title":"[부산] 동래 티씨지샵 셔플 - VANGUARD","start":"2026-04-04","allDay":true,"resultTitle":"뱅가드 샵파이트 결과","xUrl":"https://x.com/i/status/2040359839508168998"},{"title":"[서울] 당산 카드냥 - ONE PIECE","start":"2026-04-04","allDay":true,"resultTitle":"원피스 플래그쉽 배틀 결과","xUrl":"https://x.com/i/status/2040379675860750553"},{"title":"[서울] 아현 카드킹덤 - VANGUARD","start":"2026-04-04","allDay":true,"resultTitle":"뱅가드 공인 대회 결과","xUrl":"https://x.com/i/status/2040382975683006555"},{"title":"[서울] 장한평 마린포드 - ONE PIECE","start":"2026-04-04","allDay":true,"resultTitle":"원피스 플래그십 배틀 결과","xUrl":"https://x.com/i/status/2040397234542608504"},{"title":"[서울] 장한평 마린포드 - DIGIMON","start":"2026-04-04","allDay":true,"resultTitle":"디지몬 에볼루션 컵 및 테이머 배틀 결과","xUrl":"https://x.com/i/status/2040396817268158725"},{"title":"[서울] 장한평 마린포드 - YUGIOH","start":"2026-04-04","allDay":true,"resultTitle":"유희왕 무금제 및 일본판 대회 결과","xUrl":"https://x.com/i/status/2040396268535701792"},{"title":"[인천] 부평 히어로즈 - YUGIOH","start":"2026-04-04","allDay":true,"resultTitle":"유희왕 비공인대회 결과","xUrl":"https://x.com/i/status/2040395697783259328"},{"title":"[전라제주] 목포 TCG팩토리 - POKEMON","start":"2026-04-04","allDay":true,"resultTitle":"포켓몬 카드게임 미니리그 결과","xUrl":"https://x.com/i/status/2040355250595594535"},{"title":"[전라제주] 목포 TCG팩토리 - ONE PIECE","start":"2026-04-04","allDay":true,"resultTitle":"원피스 카드게임 플래그쉽 배틀 결과","xUrl":"https://x.com/i/status/2040324838708203625"},{"title":"[전라제주] 제주 TCG아일랜드 - VANGUARD","start":"2026-04-04","allDay":true,"resultTitle":"뱅가드 정기 대회 결과","xUrl":"https://x.com/i/status/2040328897603260424"},{"title":"[경기] 수원 TCG TracerZ - YUGIOH","start":"2026-04-04","allDay":true,"resultTitle":"유희왕 제 6 회 TTZ-OPC 2026 결과","xUrl":"https://x.com/i/status/2040634384781602869"},{"title":"[경남] 울산 듀얼팩토리 - DIGIMON","start":"2026-04-04","allDay":true,"resultTitle":"디지몬 테이머배틀 결과","xUrl":"https://x.com/i/status/2040755982356431251"},{"title":"[부산] 경성대 TCG 드로우 - YUGIOH","start":"2026-04-04","allDay":true,"resultTitle":"유희왕 공인풀 드로우 CS 결과","xUrl":"https://x.com/i/status/2040737478165106893"},{"title":"[부산] 양정 J클로버 - VANGUARD","start":"2026-04-04","allDay":true,"resultTitle":"카드파이트뱅가드 주말 대회 결과","xUrl":"https://x.com/i/status/2040669854412533813"},{"title":"[부산] 양정 J클로버 - ONE PIECE","start":"2026-04-04","allDay":true,"resultTitle":"원피스카드게임 주말 대회 결과","xUrl":"https://x.com/i/status/2040669854412533813"},{"title":"[부산] 양정 J클로버 - DIGIMON","start":"2026-04-04","allDay":true,"resultTitle":"디지몬카드게임 주말 대회 결과","xUrl":"https://x.com/i/status/2040669854412533813"},{"title":"[부산] 양정 J클로버 - GUNDAM","start":"2026-04-04","allDay":true,"resultTitle":"건담카드게임 주말 대회 결과","xUrl":"https://x.com/i/status/2040669854412533813"},{"title":"[서울] ABOUT TCG - ULTRAMAN","start":"2026-04-04","allDay":true,"resultTitle":"울트라맨 갤럭시 컵 결과","xUrl":"https://x.com/i/status/2041026369992511627"},{"title":"[경기] 수원 카드 플래닛 - POKEMON","start":"2026-04-04","allDay":true,"resultTitle":"포켓몬 Planet Cup 결과","xUrl":"https://x.com/i/status/2041345053847916925"},{"title":"[부산] 서면 보드게임카페 미니빌 - UNION ARENA","start":"2026-04-04","allDay":true,"resultTitle":"유니온아레나 대회 결과","xUrl":"https://x.com/i/status/2042130991855370584"},{"title":"[경기] 평택 카드빌리지 - YUGIOH","start":"2026-04-04","allDay":true,"resultTitle":"유희왕 미니대회 결과","xUrl":"https://x.com/i/status/2042502672348299757"},{"title":"[경기] 평택 카드빌리지 - DIGIMON","start":"2026-04-04","allDay":true,"resultTitle":"디지몬 테이머 배틀 대회 결과","xUrl":"https://x.com/i/status/2042502238229446743"},{"title":"[충남충북] 천안 카드빌리지 - ONE PIECE","start":"2026-04-04","allDay":true,"resultTitle":"원피스카드게임 주말 펭귄 CS 결과","xUrl":"https://x.com/i/status/2042421416558280977"},{"title":"[충남충북] 천안 카드빌리지 - NIVEL ARENA","start":"2026-04-04","allDay":true,"resultTitle":"니벨아레나 비공인 미니리그 결과","xUrl":"https://x.com/i/status/2042421095689838785"},{"title":"[충남충북] 천안 카드빌리지 - HOLOLIVE","start":"2026-04-04","allDay":true,"resultTitle":"홀로라이브 공인 샵 대회 결과","xUrl":"https://x.com/i/status/2042421012445479006"},{"title":"[경기] 수내 카드빈 - DIGIMON","start":"2026-04-03","allDay":true,"resultTitle":"디지몬 위클리 이벤트 결과","xUrl":"https://x.com/i/status/2040053397320343683"},{"title":"[경기] 수원 TCG TracerZ - YUGIOH","start":"2026-04-03","allDay":true,"resultTitle":"유희왕 금요 미니토너먼트 결과","xUrl":"https://x.com/i/status/2040034229405569173"},{"title":"[경기] 수원 TCG TracerZ - ONE PIECE","start":"2026-04-03","allDay":true,"resultTitle":"원피스 스탠다드배틀 결과","xUrl":"https://x.com/i/status/2040032839941730393"},{"title":"[경기] 안산 LAS TCG - POKEMON","start":"2026-04-03","allDay":true,"resultTitle":"포켓몬 미니리그 결과","xUrl":"https://x.com/i/status/2040052225117237281"},{"title":"[서울] 신당 카드스퀘어 - YUGIOH","start":"2026-04-03","allDay":true,"resultTitle":"유희왕 백수팬더 CS 결과","xUrl":"https://x.com/i/status/2040070314416284111"},{"title":"[서울] 장한평 마린포드 - VANGUARD","start":"2026-04-03","allDay":true,"resultTitle":"뱅가드 하기 좋은날 CS 결과","xUrl":"https://x.com/i/status/2040056954102624482"},{"title":"[서울] 장한평 마린포드 - DIGIMON","start":"2026-04-03","allDay":true,"resultTitle":"디지몬 한글판 미니대회 결과","xUrl":"https://x.com/i/status/2040046441016807710"},{"title":"[서울] 장한평 마린포드 - YUGIOH","start":"2026-04-03","allDay":true,"resultTitle":"유희왕 대회 입상 결과","xUrl":"https://x.com/i/status/2040043121606865178"},{"title":"[경기] 김포 카드베이스 - DIGIMON","start":"2026-04-03","allDay":true,"resultTitle":"디지몬 카드게임 비공인 평일 위클리 결과","xUrl":"https://x.com/i/status/2040335926740881659"},{"title":"[부산] 양정 J클로버 - YUGIOH","start":"2026-04-03","allDay":true,"resultTitle":"유희왕 OCG 평일 입상 결과","xUrl":"https://x.com/i/status/2040298787995050265"},{"title":"[부산] 양정 J클로버 - ONE PIECE","start":"2026-04-03","allDay":true,"resultTitle":"원피스 카드게임 스탠다드 입상 결과","xUrl":"https://x.com/i/status/2040298787995050265"},{"title":"[경남] 울산 던전다이스 - DIGIMON","start":"2026-04-03","allDay":true,"resultTitle":"디지몬 테이머배틀 대회 결과","xUrl":"https://x.com/i/status/2040696305622897096"},{"title":"[경남] 울산 듀얼팩토리 - POKEMON","start":"2026-04-03","allDay":true,"resultTitle":"포켓몬 공인 토너먼트 결과","xUrl":"https://x.com/i/status/2040755460547183076"},{"title":"[부산] 서면 보드게임카페 미니빌 - UNION ARENA","start":"2026-04-03","allDay":true,"resultTitle":"유니온아레나 대회 결과","xUrl":"https://x.com/i/status/2042130256883282049"},{"title":"[충남충북] 천안 카드빌리지 - ONE PIECE","start":"2026-04-03","allDay":true,"resultTitle":"원피스카드게임 스탠다드 배틀 & 펭귄 CS 결과","xUrl":"https://x.com/i/status/2042420935731618156"},{"title":"[경기] 수내 카드빈 - POKEMON","start":"2026-04-02","allDay":true,"resultTitle":"포켓몬 미니리그 공인 대회 결과","xUrl":"https://x.com/i/status/2039685060245537032"},{"title":"[경기] 안산 LAS TCG - YUGIOH","start":"2026-04-02","allDay":true,"resultTitle":"유희왕 미니리그 결과","xUrl":"https://x.com/i/status/2039689612499861978"},{"title":"[서울] 당산 카드냥 - HOLOLIVE","start":"2026-04-02","allDay":true,"resultTitle":"홀로라이브 OCG 공인 샵대회 결과","xUrl":"https://x.com/i/status/2039673967225823680"},{"title":"[서울] 잠실새내 카드스타 - NIVEL ARENA","start":"2026-04-02","allDay":true,"resultTitle":"니벨아레나 미니 대회 결과","xUrl":"https://x.com/i/status/2039681544206655732"},{"title":"[서울] 장한평 마린포드 - DIGIMON","start":"2026-04-02","allDay":true,"resultTitle":"디지몬 일본판 테이머 배틀 결과","xUrl":"https://x.com/i/status/2039680515788218721"},{"title":"[서울] 장한평 마린포드 - HOLOLIVE","start":"2026-04-02","allDay":true,"resultTitle":"홀로라이브 공인샵 대회 결과","xUrl":"https://x.com/i/status/2039679193316048939"},{"title":"[서울] 장한평 마린포드 - VANGUARD","start":"2026-04-02","allDay":true,"resultTitle":"뱅가드 일본판 미니대회 결과","xUrl":"https://x.com/i/status/2039679029402280414"},{"title":"[서울] 장한평 마린포드 - YUGIOH","start":"2026-04-02","allDay":true,"resultTitle":"유희왕 일본판 미니대회 결과","xUrl":"https://x.com/i/status/2039678761147535862"},{"title":"[서울] 장한평 마린포드 - NIVEL ARENA","start":"2026-04-02","allDay":true,"resultTitle":"니벨아레나 미니대회 결과","xUrl":"https://x.com/i/status/2039672697014366533"},{"title":"[서울] 장한평 마린포드 - ONE PIECE","start":"2026-04-02","allDay":true,"resultTitle":"원피스 한글판 대회 결과","xUrl":"https://x.com/i/status/2039672476612116915"},{"title":"[대구경북] 대구 듀얼스파크 - ONE PIECE","start":"2026-04-02","allDay":true,"resultTitle":"원피스 하치노스 CS 결과","xUrl":"https://x.com/i/status/2041474976625426686"},{"title":"[충남충북] 천안 카드빌리지 - DIGIMON","start":"2026-04-02","allDay":true,"resultTitle":"디지몬카드게임 비공인 미니리그 결과","xUrl":"https://x.com/i/status/2042420775219876119"},{"title":"[대구경북] 대구 듀얼챔프 - ONE PIECE","start":"2026-04-01","allDay":true,"resultTitle":"원피스 듀얼챔프 이벤트 결과","xUrl":"https://x.com/i/status/2039315282226028977"},{"title":"[대구경북] 대구 듀얼챔프 - HOLOLIVE","start":"2026-04-01","allDay":true,"resultTitle":"홀로라이브 듀얼챔프 이벤트 결과","xUrl":"https://x.com/i/status/2039315282226028977"},{"title":"[대구경북] 대구 듀얼챔프 - WEISS SCHWARZ","start":"2026-04-01","allDay":true,"resultTitle":"바이스 슈발츠 듀얼챔프 이벤트 결과","xUrl":"https://x.com/i/status/2039315282226028977"},{"title":"[서울] 당산 카드냥 - DIGIMON","start":"2026-04-01","allDay":true,"resultTitle":"디지몬 테이머배틀 결과","xUrl":"https://x.com/i/status/2039313637043847178"},{"title":"[서울] 잠실새내 카드스타 - VANGUARD","start":"2026-04-01","allDay":true,"resultTitle":"뱅가드 최강테 결과","xUrl":"https://x.com/i/status/2039355053618987340"},{"title":"[서울] 장한평 마린포드 - VANGUARD","start":"2026-04-01","allDay":true,"resultTitle":"뱅가드 일본판 미니대회 결과","xUrl":"https://x.com/i/status/2039312777979088945"},{"title":"[서울] 장한평 마린포드 - NIVEL ARENA","start":"2026-04-01","allDay":true,"resultTitle":"니벨아레나 미니대회 결과","xUrl":"https://x.com/i/status/2039311548272001261"},{"title":"[서울] 장한평 마린포드 - YUGIOH","start":"2026-04-01","allDay":true,"resultTitle":"유희왕 일본판 무금제 대회 결과","xUrl":"https://x.com/i/status/2039310835533983813"},{"title":"[경기] 안산 LAS TCG - SHADOWVERSE EVOLVE","start":"2026-04-01","allDay":true,"resultTitle":"섀도우버스 이볼브 공인대회 결과","xUrl":"https://x.com/i/status/2039689778162172148"},{"title":"[부산] 양정 J클로버 - VANGUARD","start":"2026-04-01","allDay":true,"resultTitle":"카드파이트뱅가드 평일 입상 결과","xUrl":"https://x.com/i/status/2039602666708533676"},{"title":"[서울] 신당 카드스퀘어 - DIGIMON","start":"2026-04-01","allDay":true,"resultTitle":"디지몬 수요일을 달리는 테이머 결과","xUrl":"https://x.com/i/status/2039647328131563872"},{"title":"[충남충북] 천안 카드빌리지 - Starlight TCG","start":"2026-04-01","allDay":true,"resultTitle":"스타라이트 TCG 공인 챌린저스 - 아이린 결과","xUrl":"https://x.com/i/status/2042420680764113103"},{"title":"[충남충북] 천안 카드빌리지 - ONE PIECE","start":"2026-04-01","allDay":true,"resultTitle":"원피스카드게임 리미티드 배틀 결과","xUrl":"https://x.com/i/status/2042420597851111592"}],"regions":["경기","경남","대구경북","부산","서울","인천","전라제주","충남충북"],"games":["DIGIMON","GUNDAM","HOLOLIVE","LUMEN CONDENSOR","NIVEL ARENA","ONE PIECE","POKEMON","SHADOWVERSE EVOLVE","Stacker Battle","Starlight TCG","ULTRAMAN","UNION ARENA","VANGUARD","WEISS SCHWARZ","YUGIOH","YUGIOH RUSH DUEL"]}